{
  "620989": {
    "name": "eeeceac",
    "tel": "9814295492"
  },
  "689876": {
    "name": "ggcfaef",
    "tel": "9541782281"
  },
  "211370": {
    "name": "eaeeaed",
    "tel": "3848733283"
  },
  "902252": {
    "name": "befgcde",
    "tel": "7019185658"
  },
  "923672": {
    "name": "edeeega",
    "tel": "5219785971"
  },
  "54429": {
    "name": "ecbdefa",
    "tel": "2852126010"
  },
  "216806": {
    "name": "ecfefaa",
    "tel": "6990672371"
  },
  "60974": {
    "name": "geabdbc",
    "tel": "6712541103"
  },
  "770887": {
    "name": "aaddcgc",
    "tel": "3712808314"
  },
  "51542": {
    "name": "geceeeg",
    "tel": "8441593424"
  },
  "14740": {
    "name": "fgbdfgd",
    "tel": "3855390896"
  },
  "391475": {
    "name": "fggaeae",
    "tel": "6247822348"
  },
  "51204": {
    "name": "abbddcc",
    "tel": "8182056121"
  },
  "37868": {
    "name": "eefeebg",
    "tel": "0932293948"
  },
  "332583": {
    "name": "fffacbe",
    "tel": "2186462477"
  },
  "919609": {
    "name": "gbbeecb",
    "tel": "0827979822"
  },
  "897989": {
    "name": "cecbdae",
    "tel": "4947081176"
  },
  "260601": {
    "name": "faafaeb",
    "tel": "0744620312"
  },
  "610403": {
    "name": "egcgfge",
    "tel": "1532403282"
  },
  "160116": {
    "name": "gadbcga",
    "tel": "7137307232"
  },
  "750279": {
    "name": "dgecaed",
    "tel": "1446454809"
  },
  "235482": {
    "name": "feegaba",
    "tel": "9029301090"
  },
  "630336": {
    "name": "edbcgca",
    "tel": "8675338244"
  },
  "14272": {
    "name": "acgecec",
    "tel": "2632948194"
  },
  "913750": {
    "name": "acbgcca",
    "tel": "4756068725"
  },
  "876192": {
    "name": "eegfcee",
    "tel": "3684443992"
  },
  "723474": {
    "name": "bgffdfg",
    "tel": "3469726542"
  },
  "307389": {
    "name": "cfeedbd",
    "tel": "2554582390"
  },
  "888938": {
    "name": "eadfeca",
    "tel": "1784895183"
  },
  "477885": {
    "name": "fafgega",
    "tel": "5596333694"
  }
}